setup.py
apollo/__init__.py
apollo/apollo_client.py
apollo/feature_switch.py
apollo/open_setting.py
didi_client.egg-info/PKG-INFO
didi_client.egg-info/SOURCES.txt
didi_client.egg-info/dependency_links.txt
didi_client.egg-info/top_level.txt
featurepalette/__init__.py
featurepalette/errno/__init__.py
featurepalette/errno/constants.py
featurepalette/errno/ttypes.py
featurepalette/response/__init__.py
featurepalette/response/constants.py
featurepalette/response/ttypes.py
featurepalette/service/FeaturePalette.py
featurepalette/service/__init__.py
featurepalette/service/constants.py
featurepalette/service/ttypes.py
featurepalette/trace/__init__.py
featurepalette/trace/constants.py
featurepalette/trace/ttypes.py