Metadata-Version: 1.1
Name: didi-client
Version: 1.0.0
Summary: apollo and feature palette client
Home-page: UNKNOWN
Author: Manni Zhang
Author-email: zhangmanni@didiglobal.com
License: UNKNOWN
Platform: UNKNOWN
Classifier: Programming Language :: Python :: 3
Classifier: License :: OSI Approved :: MIT License
Classifier: Operating System :: OS Independent
